randsho_stryx00/__init__.py
randsho_stryx00/randsho.py
randsho_stryx00-0.1.dist-info/LICENSE
randsho_stryx00-0.1.dist-info/METADATA
randsho_stryx00-0.1.dist-info/WHEEL
randsho_stryx00-0.1.dist-info/top_level.txt
randsho_stryx00-0.1.dist-info/RECORD
